{
    "referOnlyOne": 0,
    "referArr": [],
    "refer": 7162253,
    "serverGroup": [
        {
            "name": "气吞山河测试区",
            "tag": 2,
            "hide": 0,
            "name_color": "#FF0000",
            "is_cut": 1
        }
    ],
    "serverData": [
        {
            "srvid": 7162253,
            "port": 8081,
            "state": 1,
            "urlsuffix": "3.40.9",
            "mainsrvid": 7162253,
            "tag": 2,
            "h5_urlsuffix": "",
            "srvname": "气吞山河",
            "srvtopname": "",
            "name_color": "#007CFF",
            "WClientUrl": "",
            "gmurlsuffix": "",
            "pc_urlsuffix": "",
            "open_time": 1728828000,
            "show": 1,
            "show_time": 1728824400,
            "add_time": 1728823996
        }
    ],
    "gmResVer": "?v=20241011141730",
    "gmResVer_h5": "?v=20240926185331",
    "gmMapVer_h5": "?v=20240926185331",
    "gmAminVer_h5": "?v=20240926185331",
    "gmConfigVer_h5": "?v=20240926185331",
    "gmWebResVer": "?v=20241011141730",
    "gmInitResVer": "?v=20241011141730",
    "sceneResVer": "?v=20241014102749",
    "resVer": "?v=20241014102749",
    "resVer_h5": "?v=20241014161856",
    "srvRoot": "qpdg-205791.dhsf.xqhuyu.com",
    "custom": {
        "announceUrl": "http://note.zqdjy.cn/notelist/note_205791.txt",
        "hideRecharge": 0,
        "ignoreLoginBg": 0,
        "hotSizeWifi": "200",
        "hotSize4G": "200",
        "shareUrl": "https://static.dhsf.huiyuehz.com/Package/promote/dae6e95db1dd6107096c0b4796730b87.apk?v=1724835924",
        "sceneURL": "",
        "svipURL": "https://api.996box.com/svip/game/v1/",
        "payNotifyUrl": "http://pay-api.dhsf.996db.cn",
        "svipAttrURL": "https://game-api.996hezi.com",
        "copyright1": "著作权人 : 上海龙之界网络科技有限公司  著作权登记号 : 2018SR585122",
        "copyright2": "出版单位名称 : 上海科学技术文献出版社有限公司    审批文号 : 新广出审[2018]442号       出版物号 : ISBN 978-7-498-03908-8",
        "checkCodeUrl": "http://mgn-gw.tj.996sdk.com/mgn_gm_api/gm/gift/use",
        "agetipsImage": {
            "visible": 1,
            "clickTips": "1）本游戏是一款难度适中的大型多人在线角色扮演类游戏，适用于18周岁及以上的用户，建议未成年人在家长监护下使用游戏产品。%n2）本游戏的故事发生在物资丰饶的神秘土地玛法大陆上，玩家化作勇士共同抵御怪物和保卫家园，剧情叙事饱满，具有传奇色彩。游戏有丰富多样的玩法，包含角色养成、竞技等，需要投入一定的时间和精力。游戏中有基于语言和文字的陌生人社交系统，但社交系统的管理遵循相关法律法规。%n3）本游戏中有用户防沉迷、实名认证系统，未进行实名认证或实名认证为未成年人的用户将被禁止登陆游戏%n4）游戏提供了丰富的社交系统，玩家之间可以互相交流、互相配合。共同完成游戏任务，有利于促进玩家的社会交流，维持良好的社会群关系，更有良性竞争模块，带给玩家积极向上的情绪，能够增强玩家的自信心。"
        },
        "RoleRecordDoamin": "https://res.dhsf.996db.cn",
        "RoleRecordUpLoadDoamin": "https://user-sdkv2.dhsf.996db.cn",
        "showInformation": 0,
        "showInnerDeleteAccount": 0,
        "discardAgreementBSwitch": 0,
        "showDeleteAccount": 0,
        "hideChangeAccountBtn": 0,
        "icpFilingUrl": "https://beian.miit.gov.cn/#/Integrated/recordQuery",
        "icpFilingDesc": "沪ICP备12024575号-10A",
        "exchangeIsTrade": 0,
        "openReport": 0,
        "agetips": "适龄提示：适合18岁以上使用",
        "agreementUrl": [],
        "996BoxDoamin": "https://user-api.996box.com",
        "TradingBankDoamin": "http://charge-api.996box.com",
        "TradingBankPhoneDoamin": "http://user-api.996box.com",
        "996BoxLogDoamin": "http://box-collect.xqhuyu.com",
        "BaseDoamin": "http://sdk.dhsf.xqhuyu.com",
        "QRCodePayDoamin": "http://pay-sdkv2.dhsf.xqhuyu.com",
        "PCJuHeDoamin": "http://pcjuhe.dhsf.xqhuyu.com",
        "QQPayAndSensitiveWordDoamin": "https://xdwqq.dhsf.xqhuyu.com",
        "NewBaseDoamin": "http://sdkv2.dhsf.xqhuyu.com",
        "BoxNDoamin": "http://footprint.996box.com",
        "TencentDoamin": "https://openapi.minigame.qq.com",
        "BoxCloudDoamin": "https://api.996box.com",
        "996BoxDefaultDoamin": "https://tgdata.996box.com",
        "UploadServerInfoDoamin": "https://996engine.cn-hangzhou.log.aliyuncs.com",
        "TextReviewDoamin": "https://gtf.ai.xingzheai.cn",
        "ReportDoamin": "https://juhe-h5.dhsf.xqhuyu.com",
        "UploadTradingBankImageDomin": "http://uploads.996box.com",
        "NetStampHost": "https://engine-game.dhsf.996db.cn/list/",
        "visitorLinkUrl": "https://api.kf.996sdk.net/api/third/syncUserInfo",
        "cloud_phone_url": "https://api.996box.com/cloud/v1/engine/present/",
        "queryVisitorMsgUrl": "https://api.kf.996sdk.net/api/third/queryVisitorMsg",
        "clientIPUrl": "https://sdkv2.dhsf.xqhuyu.com/api/data/client_ip",
        "npOpenStatus": 1
    },
    "whitelist": [
        "10.0.175.81",
        "61.130.11.178",
        "122.224.94.82",
        "122.224.130.106",
        "183.131.177.101",
        "115.231.16.101"
    ],
    "platformId": 103200,
    "resURL": "http://hscdn.dhsf.huiyuehz.com/dhsf/cq2/",
    "resURL_h5": "//hscdn.dhsf.huiyuehz.com/h5office/",
    "resURL_ad": "http://hscdn.dhsf.huiyuehz.com/dhsf/cq2/",
    "resURL_ios": "http://hscdn.dhsf.huiyuehz.com/dhsf/cq2_ios/",
    "resURL_win": "http://hscdn.dhsf.huiyuehz.com/dhsf/cq2_win/",
    "resURL2": "http://hscdn.dhsf.xqhuyu.com/dhsf/cq2/",
    "resURL_h52": "//hscdn.dhsf.xqhuyu.com/h5office/",
    "resURL_ad2": "http://hscdn.dhsf.xqhuyu.com/dhsf/cq2/",
    "resURL_ios2": "http://hscdn.dhsf.xqhuyu.com/dhsf/cq2_ios/",
    "resURL_win2": "http://hscdn.dhsf.xqhuyu.com/dhsf/cq2_win/",
    "sceneURL": "http://hscdn.dhsf.huiyuehz.com/dhsf/box_res/",
    "gmResURL_h5": "//h5cdn-hs.dhsf.xqhuyu.com/205791/",
    "gmResURL_h52": "//hscdn.dhsf.xqhuyu.com/205791/",
    "gmResURL": "http://hscdn.dhsf.huiyuehz.com/custom/205791/hotupdate/",
    "gmResURL2": "http://hscdn.dhsf.xqhuyu.com/custom/205791/hotupdate/",
    "gmWebResURL": "http://hscdn.dhsf.huiyuehz.com/custom/205791/webres/",
    "gmWebResURL2": "http://hscdn.dhsf.xqhuyu.com/custom/205791/webres/",
    "gmInitResURL": "http://hscdn.dhsf.huiyuehz.com/custom/205791/inithotupdate/",
    "gmInitResURL2": "http://hscdn.dhsf.xqhuyu.com/custom/205791/inithotupdate/",
    "runtime": 1728894227
}